pyinline/__init__.py
pyinline/__main__.py
pyinline-0.0.2.dist-info/LICENSE
pyinline-0.0.2.dist-info/WHEEL
pyinline-0.0.2.dist-info/METADATA
pyinline-0.0.2.dist-info/RECORD
